{
    "version": "5.1.0",
    "homepage": "https://www.archimatetool.com",
    "description": "The Open Source modelling toolkit for creating ArchiMate models and sketches",
    "license": {
        "identifier": "MIT"
    },
    "url": "https://www.archimatetool.com/downloads/archi5.php?/5.1.0/Archi-Win64-5.1.0.zip",
    "hash": "07b36ff3b33f1be1732b2af12bae7500366723b8f8f9c2cefbe26daa78e57390",
    "extract_dir": "Archi",
    "shortcuts": [
        [
            "Archi.exe",
            "Archi"
        ]
    ],
    "checkver": {
        "url": "https://www.archimatetool.com/download/",
        "regex": "/downloads/archi/([\\d.]+)/Archi-"
    },
    "autoupdate": {
        "url": "https://www.archimatetool.com/downloads/archi5.php?/$version/Archi-Win64-$version.zip"
    }
}
